qualifyzedatautils/__init__.py
qualifyzedatautils/connections/RedshiftQualifyzeCluster.py
qualifyzedatautils/connections/__init__.py
qualifyzedatautils/connections/_decode_secret.py
qualifyzedatautils/connections/_retrieve_awssecret.py
qualifyzedatautils/connections/bigquery.py
qualifyzedatautils/connections/bigquery_credentials.py
qualifyzedatautils/connections/cc_bigquery.py
qualifyzedatautils/connections/cc_redshift.py
qualifyzedatautils/connections/credentials.py
qualifyzedatautils/connections/dwh_awsservicer.py
qualifyzedatautils/connections/hubspot_api_credentials.py
qualifyzedatautils/connections/redshift.py
qualifyzedatautils/connections/redshift_connection.py
qualifyzedatautils/connections/redshift_credentials.py
qualifyzedatautils/connections/secondary.py
qualifyzedatautils/dbutils/__init__.py
qualifyzedatautils/dbutils/df_bulkinsert.py
qualifyzedatautils/dbutils/df_to_redshift.py
qualifyzedatautils/dbutils/fast_df_operations.py
qualifyzedatautils/dbutils/redshift_to_df.py
qualifyzedatautils/s3utils/__init__.py
qualifyzedatautils/s3utils/file_copyrename.py
qualifyzedatautils/s3utils/file_delete.py
qualifyzedatautils/s3utils/file_read.py
qualifyzedatautils/s3utils/file_upload.py
qualifyzedatautils/sanitylogs/__init__.py
qualifyzedatautils/sanitylogs/sanitylog_insertion.py
qualifyzedatautils-3.28.dist-info/METADATA
qualifyzedatautils-3.28.dist-info/WHEEL
qualifyzedatautils-3.28.dist-info/top_level.txt
qualifyzedatautils-3.28.dist-info/RECORD
