Metadata-Version: 2.1
Name: qualifyzedatautils
Version: 3.28
Summary: Library containing the personalized utils for the DWH of Qualifyze
Home-page: http://qualifyze.com
Author: Moise O. Romaniuc Demeter
Author-email: moise.romaniuc@qualifyze.com
License: MIT
Keywords: data utils dwh qualifyze
Platform: UNKNOWN
Classifier: Development Status :: 3 - Alpha
Classifier: Topic :: Utilities
Classifier: License :: OSI Approved :: BSD License
Requires-Python: >=3.6
Requires-Dist: pandas (>=1.1.0)
Requires-Dist: psycopg2-binary (>=2.8.5)
Requires-Dist: boto3 (>=1.14.38)
Requires-Dist: awscli (>=1.18.115)
Requires-Dist: PyAthena (>=1.11.0)
